boxedfactory/__init__.py
boxedfactory/core/__init__.py
boxedfactory/core/process_worker.py
boxedfactory/core/test_worker.py
boxedfactory/core/thread_worker.py
boxedfactory/core/worker_manager.py
boxedfactory/core/common/__init__.py
boxedfactory/core/common/configurations.py
boxedfactory/core/common/cryptography.py
boxedfactory/core/common/data.py
boxedfactory/core/common/environment.py
boxedfactory/core/common/http.py
boxedfactory/core/common/queue.py
boxedfactory/core/common/shared.py
boxedfactory/core/common/storage.py
boxedfactory-1.0.1.dist-info/LICENSE
boxedfactory-1.0.1.dist-info/METADATA
boxedfactory-1.0.1.dist-info/WHEEL
boxedfactory-1.0.1.dist-info/top_level.txt
boxedfactory-1.0.1.dist-info/RECORD
