Metadata-Version: 2.1
Name: boxedfactory
Version: 1.0.1
Summary: A library for easy create and manage concurrent thread and process workers.
Home-page: https://github.com/LostSavannah/boxed-factory
Author: Erick Fernando Mora Ramirez
Author-email: erickfernandomoraramirez@gmail.com
Project-URL: Bug Tracker, https://dev.moradev.dev/boxed-factory/issues
Project-URL: Documentation, https://dev.moradev.dev/boxed-factory/documentation
Project-URL: Examples, https://dev.moradev.dev/boxed-factory/examples
Classifier: Programming Language :: Python :: 3
Classifier: Development Status :: 5 - Production/Stable
Classifier: License :: OSI Approved :: GNU General Public License v3 (GPLv3)
Classifier: Operating System :: OS Independent
Requires-Python: >=3.6
License-File: LICENSE
Requires-Dist: pydantic
Requires-Dist: fastapi
Requires-Dist: uvicorn
Requires-Dist: requests
Requires-Dist: pymongo
Requires-Dist: pika
Requires-Dist: azure-storage-blob
Requires-Dist: azure-identity
Requires-Dist: pybureaucrat
